{
	"name": "DS_2_input",
	"properties": {
		"linkedServiceName": {
			"referenceName": "LS_ADF_TO_BLOB",
			"type": "LinkedServiceReference"
		},
		"annotations": [],
		"type": "DelimitedText",
		"typeProperties": {
			"location": {
				"type": "AzureBlobStorageLocation",
				"fileName": "240826 Superstore.csv",
				"container": "input2"
			},
			"columnDelimiter": ",",
			"escapeChar": "\\",
			"firstRowAsHeader": true,
			"quoteChar": "\""
		},
		"schema": [
			{
				"name": "Row ID",
				"type": "String"
			},
			{
				"name": "Order ID",
				"type": "String"
			},
			{
				"name": "Order Date",
				"type": "String"
			},
			{
				"name": "Ship Date",
				"type": "String"
			},
			{
				"name": "Ship Mode",
				"type": "String"
			},
			{
				"name": "Customer ID",
				"type": "String"
			},
			{
				"name": "Customer Name",
				"type": "String"
			},
			{
				"name": "Segment",
				"type": "String"
			},
			{
				"name": "Country",
				"type": "String"
			},
			{
				"name": "City",
				"type": "String"
			},
			{
				"name": "State",
				"type": "String"
			},
			{
				"name": "Postal Code",
				"type": "String"
			},
			{
				"name": "Region",
				"type": "String"
			},
			{
				"name": "Product ID",
				"type": "String"
			},
			{
				"name": "Category",
				"type": "String"
			},
			{
				"name": "Sub-Category",
				"type": "String"
			},
			{
				"name": "Product Name",
				"type": "String"
			},
			{
				"name": "Sales",
				"type": "String"
			},
			{
				"name": "Quantity",
				"type": "String"
			},
			{
				"name": "Discount",
				"type": "String"
			},
			{
				"name": "Profit",
				"type": "String"
			}
		]
	}
}